{
  "categories": [
    {
      "id": 1,
      "name": "공간_거실"
    },
    {
      "id": 2,
      "name": "공간_침실"
    },
    {
      "id": 3,
      "name": "공간_화장실"
    },
    {
      "id": 4,
      "name": "공간_발코니"
    },
    {
      "id": 5,
      "name": "공간_주방"
    },
    {
      "id": 6,
      "name": "공간_현관"
    },
    {
      "id": 7,
      "name": "공간_드레스룸"
    },
    {
      "id": 8,
      "name": "공간_기타"
    },
    {
      "id": 9,
      "name": "background"
    },
    {
      "id": 10,
      "name": "구조_벽체"
    },
    {
      "id": 11,
      "name": "구조_창호"
    },
    {
      "id": 12,
      "name": "구조_출입문"
    }
  ],
  "images": [
    {
      "id": 1,
      "width": 923,
      "height": 676,
      "file_name": "51D1.jpg"
    }
  ],
  "annotations": [
    {
      "id": 1,
      "category_id": 2,
      "image_id": 1,
      "segmentation": [
        [
          842,
          339,
          603,
          339,
          607,
          348,
          658,
          348,
          661,
          357,
          640,
          390,
          599,
          405,
          600,
          654,
          843,
          651
        ]
      ],
      "area": 75193,
      "bbox": [
        599,
        339,
        244,
        315
      ],
      "iscrowd": 0,
      "room_name": "침실",
      "area_m2": 7.5
    },
    {
      "id": 2,
      "category_id": 1,
      "image_id": 1,
      "segmentation": [
        [
          732,
          138,
          404,
          137,
          396,
          275,
          350,
          272,
          349,
          199,
          247,
          200,
          243,
          342,
          83,
          346,
          87,
          652,
          589,
          651,
          593,
          274,
          729,
          268,
          674,
          257,
          733,
          204
        ]
      ],
      "area": 230980,
      "bbox": [
        83,
        137,
        650,
        515
      ],
      "iscrowd": 0,
      "room_name": "거실",
      "area_m2": 23.1
    },
    {
      "id": 3,
      "category_id": 3,
      "image_id": 1,
      "segmentation": [
        [
          84,
          122,
          82,
          128,
          84,
          194,
          152,
          195,
          157,
          182,
          167,
          176,
          190,
          189,
          198,
          190,
          198,
          122
        ]
      ],
      "area": 8182,
      "bbox": [
        82,
        122,
        116,
        73
      ],
      "iscrowd": 0,
      "room_name": "화장실",
      "area_m2": 0.8
    },
    {
      "id": 4,
      "category_id": 3,
      "image_id": 1,
      "segmentation": [
        [
          114,
          197,
          112,
          208,
          131,
          211,
          145,
          228,
          144,
          242,
          136,
          253,
          110,
          260,
          116,
          287,
          145,
          291,
          159,
          302,
          158,
          310,
          146,
          319,
          118,
          321,
          116,
          333,
          235,
          332,
          229,
          326,
          182,
          326,
          179,
          319,
          195,
          289,
          229,
          277,
          237,
          269,
          236,
          199
        ]
      ],
      "area": 12320,
      "bbox": [
        110,
        197,
        127,
        136
      ],
      "iscrowd": 0,
      "room_name": "화장실",
      "area_m2": 1.2
    },
    {
      "id": 5,
      "category_id": 6,
      "image_id": 1,
      "segmentation": [
        [
          742,
          147,
          740,
          206,
          744,
          214,
          745,
          251,
          742,
          270,
          841,
          271,
          842,
          147
        ]
      ],
      "area": 12877,
      "bbox": [
        740,
        147,
        102,
        124
      ],
      "iscrowd": 0,
      "room_name": "현관",
      "area_m2": 1.3
    },
    {
      "id": 6,
      "category_id": 7,
      "image_id": 1,
      "segmentation": [
        [
          593,
          400,
          601,
          401,
          605,
          397,
          626,
          394,
          641,
          387,
          654,
          373,
          658,
          361,
          658,
          352,
          655,
          350,
          605,
          350,
          600,
          346,
          595,
          346,
          593,
          349
        ]
      ],
      "area": 2768,
      "bbox": [
        593,
        346,
        65,
        55
      ],
      "iscrowd": 0,
      "room_name": "드레스룸",
      "area_m2": 0.3
    }
  ]
}