{
  "categories": [
    {
      "id": 1,
      "name": "공간_거실"
    },
    {
      "id": 2,
      "name": "공간_침실"
    },
    {
      "id": 3,
      "name": "공간_화장실"
    },
    {
      "id": 4,
      "name": "공간_발코니"
    },
    {
      "id": 5,
      "name": "공간_주방"
    },
    {
      "id": 6,
      "name": "공간_현관"
    },
    {
      "id": 7,
      "name": "공간_드레스룸"
    },
    {
      "id": 8,
      "name": "공간_기타"
    },
    {
      "id": 9,
      "name": "background"
    },
    {
      "id": 10,
      "name": "구조_벽체"
    },
    {
      "id": 11,
      "name": "구조_창호"
    },
    {
      "id": 12,
      "name": "구조_출입문"
    },
    {
      "id": 13,
      "name": "공간_싱크대"
    },
    {
      "id": 14,
      "name": "공간_가스레인지"
    }
  ],
  "images": [
    {
      "id": 1,
      "width": 923,
      "height": 676,
      "file_name": "201.jpg"
    }
  ],
  "annotations": [
    {
      "id": 1,
      "category_id": 3,
      "image_id": 1,
      "segmentation": [
        [
          156,
          129,
          154,
          226,
          178,
          225,
          178,
          256,
          212,
          256,
          212,
          226,
          231,
          226,
          230,
          127
        ]
      ],
      "area": 8407,
      "area_m2": null,
      "room_name": "화장실",
      "bbox": [
        154,
        127,
        77,
        129
      ],
      "iscrowd": 0
    },
    {
      "id": 2,
      "category_id": 4,
      "image_id": 1,
      "segmentation": [
        [
          233,
          96,
          233,
          177,
          296,
          176,
          296,
          96
        ]
      ],
      "area": 5072,
      "area_m2": null,
      "room_name": "발코니",
      "bbox": [
        233,
        96,
        63,
        81
      ],
      "iscrowd": 0
    },
    {
      "id": 3,
      "category_id": 4,
      "image_id": 1,
      "segmentation": [
        [
          300,
          95,
          300,
          176,
          412,
          176,
          412,
          150,
          507,
          150,
          507,
          118,
          479,
          119,
          479,
          95
        ]
      ],
      "area": 13639,
      "area_m2": null,
      "room_name": "발코니",
      "bbox": [
        300,
        95,
        207,
        81
      ],
      "iscrowd": 0
    },
    {
      "id": 4,
      "category_id": 7,
      "image_id": 1,
      "segmentation": [
        [
          234,
          182,
          296,
          183,
          296,
          349,
          155,
          348,
          154,
          261,
          234,
          261
        ]
      ],
      "area": 17248,
      "area_m2": null,
      "room_name": "드레스룸",
      "bbox": [
        154,
        182,
        142,
        167
      ],
      "iscrowd": 0
    },
    {
      "id": 5,
      "category_id": 2,
      "image_id": 1,
      "segmentation": [
        [
          155,
          353,
          156,
          515,
          316,
          515,
          314,
          356
        ]
      ],
      "area": 25598,
      "area_m2": null,
      "room_name": "침실",
      "bbox": [
        155,
        353,
        161,
        162
      ],
      "iscrowd": 0
    },
    {
      "id": 6,
      "category_id": 4,
      "image_id": 1,
      "segmentation": [
        [
          157,
          519,
          155,
          592,
          197,
          591,
          196,
          558,
          203,
          558,
          203,
          595,
          522,
          591,
          519,
          560,
          526,
          560,
          526,
          591,
          632,
          591,
          632,
          522
        ]
      ],
      "area": 33833,
      "area_m2": null,
      "room_name": "발코니",
      "bbox": [
        155,
        519,
        477,
        76
      ],
      "iscrowd": 0
    },
    {
      "id": 7,
      "category_id": 4,
      "image_id": 1,
      "segmentation": [
        [
          635,
          522,
          637,
          556,
          766,
          558,
          765,
          522
        ]
      ],
      "area": 4531,
      "area_m2": null,
      "room_name": "발코니",
      "bbox": [
        635,
        522,
        131,
        36
      ],
      "iscrowd": 0
    },
    {
      "id": 8,
      "category_id": 2,
      "image_id": 1,
      "segmentation": [
        [
          526,
          368,
          525,
          515,
          632,
          513,
          631,
          369
        ]
      ],
      "area": 15423,
      "area_m2": null,
      "room_name": "침실",
      "bbox": [
        525,
        368,
        107,
        147
      ],
      "iscrowd": 0
    },
    {
      "id": 9,
      "category_id": 2,
      "image_id": 1,
      "segmentation": [
        [
          635,
          368,
          635,
          517,
          764,
          515,
          766,
          385,
          679,
          387,
          679,
          368
        ]
      ],
      "area": 17690,
      "area_m2": null,
      "room_name": "침실",
      "bbox": [
        635,
        368,
        131,
        149
      ],
      "iscrowd": 0
    },
    {
      "id": 10,
      "category_id": 3,
      "image_id": 1,
      "segmentation": [
        [
          722,
          286,
          725,
          329,
          684,
          328,
          686,
          381,
          763,
          380,
          765,
          286
        ]
      ],
      "area": 5830,
      "area_m2": null,
      "room_name": "화장실",
      "bbox": [
        684,
        286,
        81,
        95
      ],
      "iscrowd": 0
    },
    {
      "id": 11,
      "category_id": 2,
      "image_id": 1,
      "segmentation": [
        [
          589,
          191,
          589,
          297,
          719,
          297,
          722,
          189
        ]
      ],
      "area": 14069,
      "area_m2": null,
      "room_name": "침실",
      "bbox": [
        589,
        189,
        133,
        108
      ],
      "iscrowd": 0
    },
    {
      "id": 12,
      "category_id": 5,
      "image_id": 1,
      "segmentation": [
        [
          506,
          296,
          508,
          157,
          417,
          157,
          416,
          184,
          301,
          183,
          300,
          299
        ]
      ],
      "area": 25937,
      "area_m2": null,
      "room_name": "주방",
      "bbox": [
        300,
        157,
        208,
        142
      ],
      "iscrowd": 0
    },
    {
      "id": 13,
      "category_id": 6,
      "image_id": 1,
      "segmentation": [
        [
          512,
          233,
          584,
          235,
          585,
          300,
          529,
          299,
          529,
          296,
          512,
          296
        ]
      ],
      "area": 4689,
      "area_m2": null,
      "room_name": "현관",
      "bbox": [
        512,
        233,
        73,
        67
      ],
      "iscrowd": 0
    },
    {
      "id": 14,
      "category_id": 1,
      "image_id": 1,
      "segmentation": [
        [
          680,
          303,
          300,
          300,
          300,
          349,
          322,
          349,
          320,
          515,
          522,
          514,
          522,
          360,
          680,
          359
        ]
      ],
      "area": 52974,
      "area_m2": null,
      "room_name": "거실",
      "bbox": [
        300,
        300,
        380,
        215
      ],
      "iscrowd": 0
    }
  ]
}