[
  {
    "공급사코드": "SUP-001",
    "공급사명": "OO건자재",
    "취급카테고리": [
      "방수",
      "도장"
    ],
    "리드타임": "2영업일",
    "최소주문": "10만원",
    "반품조건": "미개봉 7일",
    "결제조건": "월말정산",
    "연락처": "010-XXXX-XXXX"
  },
  {
    "공급사코드": "SUP-002",
    "공급사명": "XX세라믹",
    "취급카테고리": [
      "타일"
    ],
    "리드타임": "3~5영업일",
    "최소주문": "30만원",
    "반품조건": "파손만 교환",
    "결제조건": "선결제",
    "연락처": "010-XXXX-XXXX"
  },
  {
    "공급사코드": "SUP-003",
    "공급사명": "KCC대리점",
    "취급카테고리": [
      "도장"
    ],
    "리드타임": "1~2영업일",
    "최소주문": "5만원",
    "반품조건": "미개봉 14일",
    "결제조건": "월말정산",
    "연락처": "010-XXXX-XXXX"
  },
  {
    "공급사코드": "SUP-004",
    "공급사명": "한화마루",
    "취급카테고리": [
      "마루"
    ],
    "리드타임": "3~5영업일",
    "최소주문": "20만원",
    "반품조건": "미개봉 7일",
    "결제조건": "선결제",
    "연락처": "010-XXXX-XXXX"
  }
]